baidu_index/__init__.py
baidu_index/baidu_index.py
baidu_index/config.py
baidu_index/extended_baidu_index.py
baidu_index/utils.py
baidux/__init__.py
baidux/baidu_index.py
baidux/baidu_search.py
baidux/config.py
baidux/extended_baidu_index.py
baidux/utils.py
baidux-0.1.2.dist-info/METADATA
baidux-0.1.2.dist-info/WHEEL
baidux-0.1.2.dist-info/top_level.txt
baidux-0.1.2.dist-info/RECORD
