Metadata-Version: 2.1
Name: baidux
Version: 0.1.2
Summary: Baidu Python SDK for index and search
Home-page: https://github.com/iamsk/baidux
Author: longxiaofei
Author-email: libra.19951002@gmail.com
License: MIT
Platform: UNKNOWN
Classifier: License :: OSI Approved :: MIT License
Classifier: Programming Language :: Python
Classifier: Programming Language :: Python :: 3
Classifier: Programming Language :: Python :: 3.6
Classifier: Programming Language :: Python :: Implementation :: CPython
Classifier: Programming Language :: Python :: Implementation :: PyPy
Requires-Python: >=3.6.0
Requires-Dist: requests (>=2.19.1)
Requires-Dist: pytest (>=3.6.4)
